aio_celery/__init__.py
aio_celery/__main__.py
aio_celery/_state.py
aio_celery/amqp.py
aio_celery/annotated_task.py
aio_celery/app.py
aio_celery/backend.py
aio_celery/broker.py
aio_celery/canvas.py
aio_celery/config.py
aio_celery/context.py
aio_celery/exceptions.py
aio_celery/inspection_http_server.py
aio_celery/intermittent_gc.py
aio_celery/request.py
aio_celery/result.py
aio_celery/task.py
aio_celery/utils.py
aio_celery/worker.py
aio_celery-0.22.0.dist-info/METADATA
aio_celery-0.22.0.dist-info/WHEEL
aio_celery-0.22.0.dist-info/entry_points.txt
aio_celery-0.22.0.dist-info/top_level.txt
aio_celery-0.22.0.dist-info/RECORD
