Metadata-Version: 2.4
Name: aio-celery
Version: 0.22.0
Summary: Celery worker for running asyncio coroutine tasks
Home-page: https://github.com/earlgreyness/aio-celery
Author: Kirill Kondratenko
Author-email: earlgreatness@gmail.com
Keywords: asyncio,celery
Classifier: Development Status :: 3 - Alpha
Classifier: Topic :: System :: Distributed Computing
Classifier: Topic :: System :: Networking
Classifier: Topic :: Software Development :: Libraries
Classifier: Topic :: Software Development :: Object Brokering
Classifier: Programming Language :: Python :: Implementation :: CPython
Classifier: Programming Language :: Python :: 3
Classifier: Programming Language :: Python :: 3 :: Only
Classifier: Programming Language :: Python :: 3.8
Classifier: Programming Language :: Python :: 3.9
Classifier: Programming Language :: Python :: 3.10
Classifier: Programming Language :: Python :: 3.11
Classifier: Programming Language :: Python :: 3.12
Classifier: Intended Audience :: Developers
Classifier: Operating System :: MacOS
Classifier: Operating System :: Unix
Classifier: Operating System :: POSIX :: Linux
Classifier: Framework :: Celery
Classifier: Typing :: Typed
Requires-Python: >=3.8
Requires-Dist: aio-pika>=9.0.0
Provides-Extra: redis
Requires-Dist: redis>=4.2.0; extra == "redis"
